{  
  "_categories": [
    "fileOrigin"
  ],
  "required": [
    "species"
  ],
  "properties": {
    "additionalRemarks": {
      "type": "string",
      "_instruction": "Enter any additional remarks concerning this specimen set."
    },
    "biologicalSex": {
      "type": "array",
      "minItems": 1,
      "uniqueItems": true,
      "_instruction": "Add the biological sex of all specimen in this set.",
      "_linkedTypes": [
        "BiologicalSex"
      ]
    },
    "internalIdentifier": {
      "type": "string",
      "_instruction": "Enter the identifier (or label) of this specimen set that is used within the corresponding data files to identify this specimen set."
    },
    "lookupLabel": {
      "type": "string",
      "_instruction": "Enter a lookup label for this specimen set that may help you to find this instance more easily."
    },
    "species": {
      "type": "array",
      "minItems": 1,
      "uniqueItems": true,
      "_instruction": "Add the species and/or strain (a sub-type of a genetic variant of species) of all specimen in this set.",
      "_linkedTypes": [
        "Species",
        "Strain"
      ]
    }
  }
}
