{
  "_type": "https://openminds.ebrains.eu/core/Project",
  "required": [
    "description",
    "fullName",
    "hasResearchProducts",
    "shortName"
  ],
  "properties": {    
    "coordinator": {
      "type": "array",
      "minItems": 1,
      "uniqueItems": true,
      "_instruction": "Add all parties that coordinate this project.",
      "_linkedCategories": [
        "legalPerson"
      ]
    },
    "description": {
      "type": "string",
      "_instruction": "Enter a description of this project."
    },
    "fullName": {
      "type": "string",
      "_instruction": "Enter a descriptive full name (or title) for this project."
    },
    "hasResearchProducts": {
      "type": "array",
      "minItems": 2,
      "uniqueItems": true,
      "_instruction": "Add all research product (versions) that are part of this project.",
      "_linkedCategories": [
        "researchProduct"
      ]
    },
    "homepage": {
      "_instruction": "Add the uniform resource locator (URL) to the homepage of this project.",
      "_linkedTypes": [
        "https://openminds.ebrains.eu/core/URL"
      ]
    },
    "shortName": {
      "type": "string",
      "_instruction": "Enter a short name (or alias) for this project that could be used as a shortened display title (e.g., for web services with too little space to display the full name)."
    }
  }
}
